[
    {
        "cid": 1,
        "title": "ACG图站",
        "english": "ACG picture sites",
        "r18": false,
        "sites": [
            {
                "sid": 101,
                "title": "E-shuushuu",
                "author": "PureDark",
                "icon": "https://raw.githubusercontent.com/H-Viewer-Sites/Index/master/icons/E-shuushuu.png",
                "description": "收录图片较多且杂，但质量都不错",
                "json": "https://raw.githubusercontent.com/H-Viewer-Sites/Index/master/sites/E-shuushuu.txt",
                "versionCode": 3,
                "lastUpdate": "2016-09-27 01:36:05",
                "r18": false
            },
            {
                "sid": 102,
                "title": "Pixiv",
                "author": "PureDark",
                "icon": "https://raw.githubusercontent.com/H-Viewer-Sites/Index/master/icons/Pixiv.png",
                "description": "著名同人画、插画作品分享站点，需要登陆才能访问",
                "json": "https://raw.githubusercontent.com/H-Viewer-Sites/Index/master/sites/Pixiv.txt",
                "versionCode": 10,
                "lastUpdate": "2017-04-02 00:41:15",
                "r18": false
            },
            {
                "sid": 103,
                "title": "Bilibili 画友",
                "author": "manhong2112",
                "icon": "https://raw.githubusercontent.com/H-Viewer-Sites/Index/master/icons/Bilibili%E7%94%BB%E5%8F%8B.png",
                "description": "一个简单的原创画画交流中心",
                "json": "https://raw.githubusercontent.com/H-Viewer-Sites/Index/master/sites/Bilibili%E7%94%BB%E5%8F%8B.txt",
                "versionCode": 8,
                "lastUpdate": "2016-09-28 18:51:05",
                "r18": false
            },
            {
                "sid": 104,
                "title": "二次萌エロ画像ブログ",
                "author": "PureDark",
                "icon": "https://raw.githubusercontent.com/H-Viewer-Sites/Index/master/icons/%E4%BA%8C%E6%AC%A1%E8%90%8C%E3%82%A8%E3%83%AD%E7%94%BB%E5%83%8F%E3%83%96%E3%83%AD%E3%82%B0.png",
                "description": "エロ画像，你懂的",
                "json": "https://raw.githubusercontent.com/H-Viewer-Sites/Index/master/sites/%E4%BA%8C%E6%AC%A1%E8%90%8C%E3%82%A8%E3%83%AD%E7%94%BB%E5%83%8F%E3%83%96%E3%83%AD%E3%82%B0.txt",
                "versionCode": 4,
                "lastUpdate": "2017-06-14 16:47:12",
                "r18": true
            },
            {
                "sid": 105,
                "title": "二次元のエッチな画像",
                "author": "PureDark",
                "icon": "https://raw.githubusercontent.com/H-Viewer-Sites/Index/master/icons/%E4%BA%8C%E6%AC%A1%E5%85%83%E3%81%AE%E3%82%A8%E3%83%83%E3%83%81%E3%81%AA%E7%94%BB%E5%83%8F.png",
                "description": "也是各种エロ画像",
                "json": "https://raw.githubusercontent.com/H-Viewer-Sites/Index/master/sites/%E4%BA%8C%E6%AC%A1%E5%85%83%E3%81%AE%E3%82%A8%E3%83%83%E3%83%81%E3%81%AA%E7%94%BB%E5%83%8F.txt",
                "versionCode": 2,
                "lastUpdate": "2016-09-27 01:36:05",
                "r18": true
            },
            {
                "sid": 105,
                "title": "绝对领域",
                "author": "PureDark",
                "icon": "https://raw.githubusercontent.com/H-Viewer-Sites/Index/master/icons/%E7%BB%9D%E5%AF%B9%E9%A2%86%E5%9F%9F.png",
                "description": "一个2.5次元图片分享平台",
                "json": "https://raw.githubusercontent.com/H-Viewer-Sites/Index/master/sites/%E7%BB%9D%E5%AF%B9%E9%A2%86%E5%9F%9F.txt",
                "versionCode": 4,
                "lastUpdate": "2017-03-07 02:09:31",
                "r18": false
            },
            {
                "sid": 106,
                "title": "半次元",
                "author": "PureDark",
                "icon": "https://raw.githubusercontent.com/H-Viewer-Sites/Index/master/icons/半次元.png",
                "description": "第一中文COS绘画小说社区，需要登录才能搜索，部分内容需要登录才能浏览",
                "json": "https://raw.githubusercontent.com/H-Viewer-Sites/Index/master/sites/半次元.txt",
                "versionCode": 5,
                "lastUpdate": "2017-03-21 04:08:42",
                "r18": false
            },
            {
                "sid": 107,
                "title": "零域动漫壁纸",
                "author": "cuzfinal",
                "icon": "https://raw.githubusercontent.com/H-Viewer-Sites/Index/master/icons/零域动漫壁纸.png",
                "description": "提供好看的日本动漫卡通桌面壁纸下载，1920x1080、1920x1200、2560x1600等超高清壁纸下载，二次元可爱唯美动漫壁纸大全。更多卡通动画图片尽在零域动漫壁纸网站。",
                "json": "https://raw.githubusercontent.com/H-Viewer-Sites/Index/master/sites/零域动漫壁纸.txt",
                "versionCode": 2,
                "lastUpdate": "2017-02-17 15:09:45",
                "r18": false
            }
        ]
    },
    {
        "cid": 2,
        "title": "Booru图站",
        "english": "Booru sites",
        "r18": false,
        "sites": [
            {
                "sid": 201,
                "title": "Yande.re Post",
                "author": "PureDark",
                "icon": "https://raw.githubusercontent.com/H-Viewer-Sites/Index/master/icons/Yande.re.png",
                "description": "主收高清图，大分辨率扫描图",
                "json": "https://raw.githubusercontent.com/H-Viewer-Sites/Index/master/sites/Yande.re.Post.txt",
                "versionCode": 6,
                "lastUpdate": "2017-03-13 16:36:52",
                "r18": false
            },
            {
                "sid": 202,
                "title": "Yande.re Pool",
                "author": "PureDark",
                "icon": "https://raw.githubusercontent.com/H-Viewer-Sites/Index/master/icons/Yande.re.png",
                "description": "这是yande的图集",
                "json": "https://raw.githubusercontent.com/H-Viewer-Sites/Index/master/sites/Yande.re.Pool.txt",
                "versionCode": 2,
                "lastUpdate": "2016-09-27 01:36:05",
                "r18": false
            },
            {
                "sid": 203,
                "title": "Lolibooru Post",
                "author": "PureDark",
                "icon": "https://raw.githubusercontent.com/H-Viewer-Sites/Index/master/icons/Lolibooru.png",
                "description": "loli！loli即正义！",
                "json": "https://raw.githubusercontent.com/H-Viewer-Sites/Index/master/sites/Lolibooru.Post.txt",
                "versionCode": 6,
                "lastUpdate": "2017-03-13 16:36:52",
                "r18": true
            },
            {
                "sid": 204,
                "title": "Lolibooru Pool",
                "author": "PureDark",
                "icon": "https://raw.githubusercontent.com/H-Viewer-Sites/Index/master/icons/Lolibooru.png",
                "description": "loli的图集",
                "json": "https://raw.githubusercontent.com/H-Viewer-Sites/Index/master/sites/Lolibooru.Pool.txt",
                "versionCode": 2,
                "lastUpdate": "2016-09-27 01:36:05",
                "r18": true
            },
            {
                "sid": 205,
                "title": "Konachan Post",
                "author": "PureDark",
                "icon": "https://raw.githubusercontent.com/H-Viewer-Sites/Index/master/icons/Konachan.png",
                "description": "主收各类动漫壁纸",
                "json": "https://raw.githubusercontent.com/H-Viewer-Sites/Index/master/sites/Konachan.Post.txt",
                "versionCode": 6,
                "lastUpdate": "2017-03-13 16:36:52",
                "r18": false
            },
            {
                "sid": 206,
                "title": "Konachan Pool",
                "author": "PureDark",
                "icon": "https://raw.githubusercontent.com/H-Viewer-Sites/Index/master/icons/Konachan.png",
                "description": "Konachan图集",
                "json": "https://raw.githubusercontent.com/H-Viewer-Sites/Index/master/sites/Konachan.Pool.txt",
                "versionCode": 2,
                "lastUpdate": "2016-09-27 01:36:05",
                "r18": false
            },
            {
                "sid": 207,
                "title": "3dbooru Post",
                "author": "PureDark",
                "icon": "https://raw.githubusercontent.com/H-Viewer-Sites/Index/master/icons/3dbooru.png",
                "description": "真人cosplay图片站",
                "json": "https://raw.githubusercontent.com/H-Viewer-Sites/Index/master/sites/3dbooru.Post.txt",
                "versionCode": 6,
                "lastUpdate": "2017-03-13 16:36:52",
                "r18": false
            },
            {
                "sid": 208,
                "title": "3dbooru Pool",
                "author": "PureDark",
                "icon": "https://raw.githubusercontent.com/H-Viewer-Sites/Index/master/icons/3dbooru.png",
                "description": "3dbooru的图集",
                "json": "https://raw.githubusercontent.com/H-Viewer-Sites/Index/master/sites/3dbooru.Pool.txt",
                "versionCode": 2,
                "lastUpdate": "2016-09-27 01:36:05",
                "r18": false
            },
            {
                "sid": 209,
                "title": "Gelbooru Post",
                "author": "PureDark",
                "icon": "https://raw.githubusercontent.com/H-Viewer-Sites/Index/master/icons/Gelbooru.png",
                "description": "做的最大的booru站之一",
                "json": "https://raw.githubusercontent.com/H-Viewer-Sites/Index/master/sites/Gelbooru.Post.txt",
                "versionCode": 6,
                "lastUpdate": "2017-03-13 16:36:52",
                "r18": false
            },
            {
                "sid": 210,
                "title": "Gelbooru Pool",
                "author": "PureDark",
                "icon": "https://raw.githubusercontent.com/H-Viewer-Sites/Index/master/icons/Gelbooru.png",
                "description": "Gelbooru的图集",
                "json": "https://raw.githubusercontent.com/H-Viewer-Sites/Index/master/sites/Gelbooru.Pool.txt",
                "versionCode": 2,
                "lastUpdate": "2016-09-27 01:36:05",
                "r18": false
            },
            {
                "sid": 211,
                "title": "Xbooru Post",
                "author": "PureDark",
                "icon": "https://raw.githubusercontent.com/H-Viewer-Sites/Index/master/icons/Xbooru.png",
                "description": "这个站的图非常杂乱，而且基本以H图为主",
                "json": "https://raw.githubusercontent.com/H-Viewer-Sites/Index/master/sites/Xbooru.Post.txt",
                "versionCode": 6,
                "lastUpdate": "2017-03-13 16:36:52",
                "r18": true
            },
            {
                "sid": 212,
                "title": "Xbooru Pool",
                "author": "PureDark",
                "icon": "https://raw.githubusercontent.com/H-Viewer-Sites/Index/master/icons/Xbooru.png",
                "description": "Xbooru的图集",
                "json": "https://raw.githubusercontent.com/H-Viewer-Sites/Index/master/sites/Xbooru.Pool.txt",
                "versionCode": 2,
                "lastUpdate": "2016-09-27 01:36:05",
                "r18": true
            }
        ]
    },
    {
        "cid": 3,
        "title": "绅士漫画站",
        "english": "Hentai manga sites",
        "r18": true,
        "sites": [
            {
                "sid": 301,
                "title": "Lofi.E-hentai",
                "author": "PureDark",
                "icon": "https://raw.githubusercontent.com/H-Viewer-Sites/Index/master/icons/Ehentai.png",
                "description": "E绅士的移动版，优点是能在列表就读取到TAG，缺点是图片画质较低",
                "json": "https://raw.githubusercontent.com/H-Viewer-Sites/Index/master/sites/lofi.e-hentai.txt",
                "versionCode": 3,
                "lastUpdate": "2017-04-06 14:21:15",
                "r18": true
            },
            {
                "sid": 302,
                "title": "G.E-hentai",
                "author": "PureDark",
                "icon": "https://raw.githubusercontent.com/H-Viewer-Sites/Index/master/icons/Ehentai.png",
                "description": "E绅士的桌面版，图片较清楚，登录可查看最新内容",
                "json": "https://raw.githubusercontent.com/H-Viewer-Sites/Index/master/sites/g.e-hentai.txt",
                "versionCode": 6,
                "lastUpdate": "2018-03-29 14:23:45",
                "r18": true
            },
            {
                "sid": 303,
                "title": "Ex-hentai",
                "author": "PureDark",
                "icon": "https://raw.githubusercontent.com/H-Viewer-Sites/Index/master/icons/Ehentai.png",
                "description": "E绅士的里区，必须登录才能访问",
                "json": "https://raw.githubusercontent.com/H-Viewer-Sites/Index/master/sites/exhentai.txt",
                "versionCode": 7,
                "lastUpdate": "2018-03-29 14:23:45",
                "r18": true
            },
            {
                "sid": 304,
                "title": "绅士漫画",
                "author": "PureDark",
                "icon": "https://raw.githubusercontent.com/H-Viewer-Sites/Index/master/icons/wnacg.png",
                "description": "专注分享汉化本子",
                "json": "https://raw.githubusercontent.com/H-Viewer-Sites/Index/master/sites/wnacg.txt",
                "versionCode": 4,
                "lastUpdate": "2017-04-06 14:21:15",
                "r18": true
            },
            {
                "sid": 305,
                "title": "nhentai",
                "author": "PureDark",
                "icon": "https://raw.githubusercontent.com/H-Viewer-Sites/Index/master/icons/nhentai.png",
                "description": "本子站，最大的优点是没有被墙",
                "json": "https://raw.githubusercontent.com/H-Viewer-Sites/Index/master/sites/nhentai.txt",
                "versionCode": 5,
                "lastUpdate": "2018-03-09 06:16:15",
                "r18": true
            },
            {
                "sid": 306,
                "title": "177漫画",
                "author": "PureDark",
                "description": "收录的漫画以汉化单行本为主",
                "json": "https://raw.githubusercontent.com/H-Viewer-Sites/Index/master/sites/177%E6%BC%AB%E7%94%BB.txt",
                "versionCode": 4,
                "lastUpdate": "2017-09-24 16:29:15",
                "r18": true
            },
            {
                "sid": 307,
                "title": "エロ漫画同人誌",
                "author": "sosmygirl",
                "icon": "https://raw.githubusercontent.com/H-Viewer-Sites/Index/master/icons/%E3%82%A8%E3%83%AD%E6%BC%AB%E7%94%BB%E5%90%8C%E4%BA%BA%E8%AA%8C.png",
                "description": "一个专注同人本子的网站（炮姐，Rem应有尽有）",
                "json": "https://raw.githubusercontent.com/H-Viewer-Sites/Index/master/sites/%E3%82%A8%E3%83%AD%E6%BC%AB%E7%94%BB%E5%90%8C%E4%BA%BA%E8%AA%8C.txt",
                "versionCode": 3,
                "lastUpdate": "2016-10-04 15:57:34",
                "r18": true
            },
            {
                "sid": 308,
                "title": "H-Manga.moe",
                "author": "sosmygirl",
                "icon": "https://raw.githubusercontent.com/H-Viewer-Sites/Index/master/icons/H-Manga.moe.png",
                "description": "在线绅士同人志阅览，免费且每日更新。",
                "json": "https://raw.githubusercontent.com/H-Viewer-Sites/Index/master/sites/H-Manga.moe.txt",
                "versionCode": 4,
                "lastUpdate": "2017-03-21 04:08:34",
                "r18": true
            },
            {
                "sid": 309,
                "title": "萌春画",
                "author": "sosmygirl",
                "icon": "https://raw.githubusercontent.com/H-Viewer-Sites/Index/master/icons/%E8%90%8C%E6%98%A5%E7%94%BB.png",
                "description": "萌春画はえっちで萌えれるエロ同人誌、エロ漫画を載せています。現在フルカラー物のみで更新中！",
                "json": "https://raw.githubusercontent.com/H-Viewer-Sites/Index/master/sites/%E8%90%8C%E6%98%A5%E7%94%BB.txt",
                "versionCode": 3,
                "lastUpdate": "2017-03-21 04:08:34",
                "r18": true
            },
            {
                "sid": 310,
                "title": "Hentai.Cafe",
                "author": "PureDark",
                "icon": "https://raw.githubusercontent.com/H-Viewer-Sites/Index/master/icons/default.png",
                "description": "All the H(appiness)",
                "json": "https://raw.githubusercontent.com/H-Viewer-Sites/Index/master/sites/Hentai.Cafe.txt",
                "versionCode": 2,
                "lastUpdate": "2018-03-17 11:35:56",
                "r18": true
            },
            {
                "sid": 311,
                "title": "松鼠症仓库",
                "author": "PureDark",
                "icon": "https://raw.githubusercontent.com/H-Viewer-Sites/Index/master/icons/松鼠症仓库.png",
                "description": "松鼠症倉庫 成人漫畫區,H漫畫,超過三萬本漫畫分享您閱讀及下載!",
                "json": "https://raw.githubusercontent.com/H-Viewer-Sites/Index/master/sites/松鼠症仓库.txt",
                "versionCode": 1,
                "lastUpdate": "2018-03-17 10:31:24",
                "r18": true
            }
        ]
    },
    {
        "cid": 4,
        "title": "写真图站",
        "english": "Nude Photography Sites",
        "r18": false,
        "sites": [
            {
                "sid": 401,
                "title": "秀人",
                "author": "PureDark",
                "icon": "https://raw.githubusercontent.com/H-Viewer-Sites/Index/master/icons/%E7%A7%80%E4%BA%BA.png",
                "description": "专注模特写真及周边产业的互动平台",
                "json": "https://raw.githubusercontent.com/H-Viewer-Sites/Index/master/sites/%E7%A7%80%E4%BA%BA.txt",
                "versionCode": 3,
                "lastUpdate": "2017-03-13 09:41:23",
                "r18": false
            },
            {
                "sid": 402,
                "title": "Rosi",
                "author": "vvyoko",
                "icon": "https://raw.githubusercontent.com/H-Viewer-Sites/Index/master/icons/Rosi.png",
                "description": "性感美女写真",
                "json": "https://raw.githubusercontent.com/H-Viewer-Sites/Index/master/sites/Rosi.txt",
                "versionCode": 4,
                "lastUpdate": "2017-03-21 04:08:16",
                "r18": false
            },
            {
                "sid": 403,
                "title": "妹子图",
                "author": "PureDark",
                "icon": "https://raw.githubusercontent.com/H-Viewer-Sites/Index/master/icons/%E5%A6%B9%E5%AD%90%E5%9B%BE.png",
                "description": "每日分享最新最全最优质的妹子图片和高清性感美女图片",
                "json": "https://raw.githubusercontent.com/H-Viewer-Sites/Index/master/sites/%E5%A6%B9%E5%AD%90%E5%9B%BE.txt",
                "versionCode": 4,
                "lastUpdate": "2016-09-30 03:46:15",
                "r18": false
            },
            {
                "sid": 404,
                "title": "妹子图2",
                "author": "sosmygirl",
                "icon": "https://raw.githubusercontent.com/H-Viewer-Sites/Index/master/icons/%E5%A6%B9%E5%AD%90%E5%9B%BE2.png",
                "description": "无论是小清新,模特,还是其他妹子,我们每天都精挑细选,精彩的妹子图每天都有不一样的呈现",
                "json": "https://raw.githubusercontent.com/H-Viewer-Sites/Index/master/sites/%E5%A6%B9%E5%AD%90%E5%9B%BE2.txt",
                "versionCode": 3,
                "lastUpdate": "2016-10-03 23:22:13",
                "r18": false
            },
            {
                "sid": 405,
                "title": "美女图片集",
                "author": "PureDark",
                "icon": "https://raw.githubusercontent.com/H-Viewer-Sites/Index/master/icons/美女图片集.png",
                "description": "「美女图片集」是一个干净利落的美女图片分享社区。你会以绝佳的横向浏览方式欣赏媛馆、尤果网、推女郎等国模写真；杉原杏璃、筱崎爱、原干惠等日本女优的经典写真集怎能错过；还有欧美美女出境的黑白人体艺术摄影，脱而不露的致命诱惑。",
                "json": "https://raw.githubusercontent.com/H-Viewer-Sites/Index/master/sites/美女图片集.txt",
                "versionCode": 4,
                "lastUpdate": "2016-10-16 04:13:53",
                "r18": false
            },
            {
                "sid": 406,
                "title": "Nude-Atlas",
                "author": "PureDark",
                "icon": "https://raw.githubusercontent.com/H-Viewer-Sites/Index/master/icons/Nude-Atlas.png",
                "description": "国外的裸体写真站，各国的都有",
                "json": "https://raw.githubusercontent.com/H-Viewer-Sites/Index/master/sites/Nude-Atlas.txt",
                "versionCode": 5,
                "lastUpdate": "2016-10-16 04:45:53",
                "r18": false
            },
            {
                "sid": 407,
                "title": "宅男女神",
                "author": "PureDark",
                "icon": "https://raw.githubusercontent.com/H-Viewer-Sites/Index/master/icons/宅男女神.png",
                "description": "分享最全的宅男女神资料,最高清的美女图片,推女神,美媛馆等精品美女套图,最新的美女博客私房照,绝对不容错过！看美女就像喝水,每天都是必须的！",
                "json": "https://raw.githubusercontent.com/H-Viewer-Sites/Index/master/sites/宅男女神.txt",
                "versionCode": 2,
                "lastUpdate": "2016-10-16 05:10:26",
                "r18": false
            }
        ]
    },
    {
        "cid": 5,
        "title": "真人图站",
        "english": "Reality Sites",
        "r18": true,
        "sites": [
            {
                "sid": 501,
                "title": "草榴社区",
                "author": "PureDark",
                "icon": "https://raw.githubusercontent.com/H-Viewer-Sites/Index/master/icons/1024.png",
                "description": "1024毋须多言",
                "json": "https://raw.githubusercontent.com/H-Viewer-Sites/Index/master/sites/1024.txt",
                "versionCode": 4,
                "lastUpdate": "2016-11-28 00:16:46",
                "r18": true
            },
            {
                "sid": 502,
                "title": "AVMOO",
                "author": "PureDark",
                "icon": "https://raw.githubusercontent.com/H-Viewer-Sites/Index/master/icons/AVMOO.png",
                "description": "你的线上日本成人影片情报站。管理你的影片并分享你的想法。",
                "json": "https://raw.githubusercontent.com/H-Viewer-Sites/Index/master/sites/AVMOO.txt",
                "versionCode": 3,
                "lastUpdate": "2016-10-15 03:58:53",
                "r18": true
            },
            {
                "sid": 503,
                "title": "AVMEMO",
                "author": "PureDark",
                "icon": "https://raw.githubusercontent.com/H-Viewer-Sites/Index/master/icons/AVMEMO.png",
                "description": "你的线上欧美成人影片情报站。管理你的影片并分享你的想法。",
                "json": "https://raw.githubusercontent.com/H-Viewer-Sites/Index/master/sites/AVMEMO.txt",
                "versionCode": 3,
                "lastUpdate": "2016-10-15 03:58:36",
                "r18": true
            },
            {
                "sid": 504,
                "title": "モモんガッ(･∀･)!!",
                "author": "Ryogiakira",
                "icon": "https://raw.githubusercontent.com/H-Viewer-Sites/Index/master/icons/%E3%83%A2%E3%83%A2%E3%82%93%E3%82%AC%E3%83%83(%EF%BD%A5%E2%88%80%EF%BD%A5)!!.png",
                "description": "ＪＫ・素人・盗撮・投稿・流出などのエロ画像を中心にオリジナルなまとめ方で毎日更新してるお茶目なＲ１８エログです。",
                "json": "https://raw.githubusercontent.com/H-Viewer-Sites/Index/master/sites/%E3%83%A2%E3%83%A2%E3%82%93%E3%82%AC%E3%83%83(%EF%BD%A5%E2%88%80%EF%BD%A5)!!.txt",
                "versionCode": 2,
                "lastUpdate": "2016-10-07 13:18:16",
                "r18": true
            },
            {
                "sid": 505,
                "title": "お宝エログ幕府",
                "author": "Ryogiakira",
                "icon": "https://raw.githubusercontent.com/H-Viewer-Sites/Index/master/icons/お宝エログ幕府.png",
                "description": "2chまとめ画像ブログ",
                "json": "https://raw.githubusercontent.com/H-Viewer-Sites/Index/master/sites/お宝エログ幕府.txt",
                "versionCode": 2,
                "lastUpdate": "2016-10-07 13:18:16",
                "r18": true
            },
            {
                "sid": 506,
                "title": "ぷるるんお宝画像庫",
                "author": "Ryogiakira",
                "icon": "https://raw.githubusercontent.com/H-Viewer-Sites/Index/master/icons/ぷるるんお宝画像庫.png",
                "description": "巨乳,アイドル,画像,巨乳画像,巨乳アイドル,動画,AV,ぷるるんお宝画像庫",
                "json": "https://raw.githubusercontent.com/H-Viewer-Sites/Index/master/sites/ぷるるんお宝画像庫.txt",
                "versionCode": 2,
                "lastUpdate": "2016-10-07 13:18:16",
                "r18": true
            },
            {
                "sid": 507,
                "title": "エロ画像すももちゃんねる",
                "author": "Ryogiakira",
                "icon": "https://raw.githubusercontent.com/H-Viewer-Sites/Index/master/icons/エロ画像すももちゃんねる.png",
                "description": "エロ画像すももちゃんねる,エロ画像,AV女優,画像,エロ,AV",
                "json": "https://raw.githubusercontent.com/H-Viewer-Sites/Index/master/sites/エロ画像すももちゃんねる.txt",
                "versionCode": 2,
                "lastUpdate": "2016-10-07 13:18:16",
                "r18": true
            },
            {
                "sid": 508,
                "title": "みんくちゃんねる",
                "author": "Ryogiakira",
                "icon": "https://raw.githubusercontent.com/H-Viewer-Sites/Index/master/icons/みんくちゃんねる.png",
                "description": "エロ系2chまとめ、Twitterまとめ",
                "json": "https://raw.githubusercontent.com/H-Viewer-Sites/Index/master/sites/みんくちゃんねる.txt",
                "versionCode": 2,
                "lastUpdate": "2016-10-07 13:18:16",
                "r18": true
            },
            {
                "sid": 509,
                "title": "エロチカ",
                "author": "Ryogiakira",
                "icon": "https://raw.githubusercontent.com/H-Viewer-Sites/Index/master/icons/エロチカ.png",
                "description": "AVやグラドル・女神最新動画像まとめ",
                "json": "https://raw.githubusercontent.com/H-Viewer-Sites/Index/master/sites/エロチカ.txt",
                "versionCode": 2,
                "lastUpdate": "2016-10-07 13:18:16",
                "r18": true
            }
        ]
    },
    {
        "cid": 5,
        "title": "素材图站",
        "english": "Resource Sites",
        "r18": false,
        "sites": [
            {
                "sid": 501,
                "title": "Dribbble",
                "author": "PureDark",
                "icon": "https://raw.githubusercontent.com/H-Viewer-Sites/Index/master/icons/Dribbble.png",
                "description": "艺术工作者、设计师创作作品交流网站",
                "json": "https://raw.githubusercontent.com/H-Viewer-Sites/Index/master/sites/Dribbble.txt",
                "versionCode": 4,
                "lastUpdate": "2016-10-20 06:14:15",
                "r18": false
            },
            {
                "sid": 502,
                "title": "UI中国",
                "author": "PureDark",
                "icon": "https://raw.githubusercontent.com/H-Viewer-Sites/Index/master/icons/UI%E4%B8%AD%E5%9B%BD.png",
                "description": "专业界面交互设计平台",
                "json": "https://raw.githubusercontent.com/H-Viewer-Sites/Index/master/sites/UI%E4%B8%AD%E5%9B%BD.txt",
                "versionCode": 4,
                "lastUpdate": "2016-10-20 06:15:15",
                "r18": false
            },
            {
                "sid": 503,
                "title": "花瓣网-采集",
                "author": "PureDark",
                "icon": "https://raw.githubusercontent.com/H-Viewer-Sites/Index/master/icons/花瓣网.png",
                "description": "设计师寻找灵感的天堂！图片素材领导者，帮你采集,发现网络上你喜欢的事物.你可以用它收集灵感,保存有用的素材,计划旅行,晒晒自己想要的东西；添加后长按编辑站点，修改“我的采集”的网址",
                "json": "https://raw.githubusercontent.com/H-Viewer-Sites/Index/master/sites/花瓣网-采集.txt",
                "versionCode": 3,
                "lastUpdate": "2017-03-30 00:09:29",
                "r18": false
            },
            {
                "sid": 504,
                "title": "花瓣网-画板",
                "author": "PureDark",
                "icon": "https://raw.githubusercontent.com/H-Viewer-Sites/Index/master/icons/花瓣网.png",
                "description": "设计师寻找灵感的天堂！图片素材领导者，帮你采集,发现网络上你喜欢的事物.你可以用它收集灵感,保存有用的素材,计划旅行,晒晒自己想要的东西；添加后长按编辑站点，修改“关注画板”的网址",
                "json": "https://raw.githubusercontent.com/H-Viewer-Sites/Index/master/sites/花瓣网-画板.txt",
                "versionCode": 5,
                "lastUpdate": "2017-05-04 19:34:29",
                "r18": false
            },
            {
                "sid": 505,
                "title": "Pinterest",
                "author": "PureDark",
                "icon": "https://raw.githubusercontent.com/H-Viewer-Sites/Index/master/icons/Pinterest.png",
                "description": "通过图片墙Pinboard发布图片，瀑布流展示图片，不断发现新的图片，必须要登录才能浏览",
                "json": "https://raw.githubusercontent.com/H-Viewer-Sites/Index/master/sites/Pinterest.txt",
                "versionCode": 2,
                "lastUpdate": "2016-10-20 06:16:29",
                "r18": false
            },
            {
                "sid": 506,
                "title": "Tumblr",
                "author": "PureDark",
                "icon": "https://raw.githubusercontent.com/H-Viewer-Sites/Index/master/icons/Tumblr.png",
                "description": "目前全球最大的轻博客网站，也是轻博客网站的始祖，目前暂不支持登录显示订阅",
                "json": "https://raw.githubusercontent.com/H-Viewer-Sites/Index/master/sites/Tumblr.txt",
                "versionCode": 3,
                "lastUpdate": "2017-03-30 00:09:54",
                "r18": false
            },
            {
                "sid": 507,
                "title": "优美图库",
                "author": "zhouzistudio",
                "icon": "https://raw.githubusercontent.com/H-Viewer-Sites/Index/master/icons/优美图库.png",
                "description": "美女图片、发型图片、唯美图片、头像图片等好看的图片大全，找美女图片大全、性感美图、好看的图片大全就到优美图库",
                "json": "https://raw.githubusercontent.com/H-Viewer-Sites/Index/master/sites/优美图库.txt",
                "versionCode": 1,
                "lastUpdate": "2017-05-03 02:25:12",
                "r18": false
            }
        ]
    },
    {
        "cid": 6,
        "title": "视频站",
        "english": "Video Sites",
        "r18": false,
        "sites": [
            {
                "sid": 601,
                "title": "H-Anime",
                "author": "PureDark",
                "icon": "https://raw.githubusercontent.com/H-Viewer-Sites/Index/master/icons/H-Anime.png",
                "description": "在线观看绅士动画，经常更新，与时俱进",
                "json": "https://raw.githubusercontent.com/H-Viewer-Sites/Index/master/sites/H-Anime.txt",
                "versionCode": 3,
                "lastUpdate": "2017-04-28 09:22:15",
                "r18": true
            },
            {
                "sid": 602,
                "title": "Hentai Play",
                "author": "PureDark",
                "icon": "https://raw.githubusercontent.com/H-Viewer-Sites/Index/master/icons/Hentai-Play.png",
                "description": "最新的、英文字幕的绅士动画。 上千部每日更新的动画可供在线观看!",
                "json": "https://raw.githubusercontent.com/H-Viewer-Sites/Index/master/sites/Hentai-Play.txt",
                "versionCode": 3,
                "lastUpdate": "2017-04-28 09:22:15",
                "r18": true
            },
            {
                "sid": 603,
                "title": "Pornhub",
                "author": "PureDark",
                "icon": "https://raw.githubusercontent.com/H-Viewer-Sites/Index/master/icons/Pornhub.png",
                "description": "全世界最大的成人视频网站还需要我介绍吗",
                "json": "https://raw.githubusercontent.com/H-Viewer-Sites/Index/master/sites/Pornhub.txt",
                "versionCode": 2,
                "lastUpdate": "2017-03-02 19:19:15",
                "r18": true
            },
            {
                "sid": 604,
                "title": "XVIDEOS",
                "author": "PureDark",
                "icon": "https://raw.githubusercontent.com/H-Viewer-Sites/Index/master/icons/xvideos.png",
                "description": "另一个在线视频网站",
                "json": "https://raw.githubusercontent.com/H-Viewer-Sites/Index/master/sites/xvideos.txt",
                "versionCode": 2,
                "lastUpdate": "2017-02-17 16:25:12",
                "r18": true
            },
            {
                "sid": 605,
                "title": "Iwara-動画",
                "author": "PureDark",
                "icon": "https://raw.githubusercontent.com/H-Viewer-Sites/Index/master/icons/Iwara.png",
                "description": "I站上有大量R18的MMD动画",
                "json": "https://raw.githubusercontent.com/H-Viewer-Sites/Index/master/sites/Iwara-video.txt",
                "versionCode": 2,
                "lastUpdate": "2017-07-23 22:41:12",
                "r18": true
            },
            {
                "sid": 606,
                "title": "Iwara-画像",
                "author": "PureDark",
                "icon": "https://raw.githubusercontent.com/H-Viewer-Sites/Index/master/icons/Iwara.png",
                "description": "I站另一部分是画像区，因目测规则无法实现合并，暂时分成两个站点",
                "json": "https://raw.githubusercontent.com/H-Viewer-Sites/Index/master/sites/Iwara-image.txt",
                "versionCode": 2,
                "lastUpdate": "2017-07-23 22:41:12",
                "r18": true
            },
            {
                "sid": 607,
                "title": "HPJav",
                "author": "PureDark",
                "icon": "https://raw.githubusercontent.com/H-Viewer-Sites/Index/master/icons/HPJav.png",
                "description": "JAV線上看, 中文字幕JAV, 日本有碼, 無碼 ,JAV Online HPJAV",
                "json": "https://raw.githubusercontent.com/H-Viewer-Sites/Index/master/sites/HPJav.txt",
                "versionCode": 3,
                "lastUpdate": "2018-03-17 05:17:19",
                "r18": true
            },
            {
                "sid": 608,
                "title": "YouAv",
                "author": "PureDark",
                "icon": "https://raw.githubusercontent.com/H-Viewer-Sites/Index/master/icons/youav.png",
                "description": "YOUAV免費無碼高清在線成人影片, 情色電影。",
                "json": "https://raw.githubusercontent.com/H-Viewer-Sites/Index/master/sites/youav.txt",
                "versionCode": 1,
                "lastUpdate": "2018-03-17 07:18:28",
                "r18": true
            }
        ]
    }
]